<?xml version="1.0" encoding="UTF-8"?>
<!--(C) EIOPA - XBRL Taxonomy-->
<?officialURI http://eiopa.europa.eu/eu/xbrl/s2md/fws/solvency/solvency2/2019-07-15/tab/s.27.01.01.20/s.27.01.01.20-lab-codes.xml?>
<?taxonomy-version 2.4.0?>
<?taxonomy-date 2019-07-15?>
<link:linkbase xmlns:xsi="http://www.w3.org/2001/XMLSchema-instance" xmlns:xlink="http://www.w3.org/1999/xlink" xmlns:link="http://www.xbrl.org/2003/linkbase" xmlns:gen="http://xbrl.org/2008/generic" xmlns:label="http://xbrl.org/2008/label" xsi:schemaLocation="http://www.xbrl.org/2003/linkbase http://www.xbrl.org/2003/xbrl-linkbase-2003-12-31.xsd http://xbrl.org/2008/generic http://www.xbrl.org/2008/generic-link.xsd http://xbrl.org/2008/label http://www.xbrl.org/2008/generic-label.xsd">
  <link:arcroleRef arcroleURI="http://xbrl.org/arcrole/2008/element-label" xlink:type="simple" xlink:href="http://www.xbrl.org/2008/generic-label.xsd#element-label" />
  <link:roleRef roleURI="http://www.eurofiling.info/xbrl/role/filing-indicator-code" xlink:type="simple" xlink:href="http://www.eurofiling.info/eu/fr/xbrl/ext/model.xsd#filing-indicator-code" />
  <link:roleRef roleURI="http://www.eurofiling.info/xbrl/role/rc-code" xlink:type="simple" xlink:href="http://www.eurofiling.info/eu/fr/xbrl/ext/model.xsd#rc-code" />
  <gen:link xlink:type="extended" xlink:role="http://www.xbrl.org/2003/role/link">
    <link:loc xlink:type="locator" xlink:href="s.27.01.01.20-rend.xml#s2md_tS.27.01.01.20" xlink:label="loc_s2md_tS.27.01.01.20" />
    <label:label xlink:type="resource" xlink:label="label_s2md_tS.27.01.01.20" xml:lang="en" xlink:role="http://www.eurofiling.info/xbrl/role/rc-code">S.27.01.01.20</label:label>
    <gen:arc xlink:type="arc" xlink:arcrole="http://xbrl.org/arcrole/2008/element-label" xlink:from="loc_s2md_tS.27.01.01.20" xlink:to="label_s2md_tS.27.01.01.20" />
    <link:loc xlink:type="locator" xlink:href="s.27.01.01.20-rend.xml#s2md_c7436" xlink:label="loc_s2md_c7436" />
    <label:label xlink:type="resource" xlink:label="label_s2md_c7436" xml:lang="en" xlink:role="http://www.eurofiling.info/xbrl/role/rc-code">C1170</label:label>
    <gen:arc xlink:type="arc" xlink:arcrole="http://xbrl.org/arcrole/2008/element-label" xlink:from="loc_s2md_c7436" xlink:to="label_s2md_c7436" />
    <link:loc xlink:type="locator" xlink:href="s.27.01.01.20-rend.xml#s2md_c7437" xlink:label="loc_s2md_c7437" />
    <label:label xlink:type="resource" xlink:label="label_s2md_c7437" xml:lang="en" xlink:role="http://www.eurofiling.info/xbrl/role/rc-code">C1180</label:label>
    <gen:arc xlink:type="arc" xlink:arcrole="http://xbrl.org/arcrole/2008/element-label" xlink:from="loc_s2md_c7437" xlink:to="label_s2md_c7437" />
    <link:loc xlink:type="locator" xlink:href="s.27.01.01.20-rend.xml#s2md_c7439" xlink:label="loc_s2md_c7439" />
    <label:label xlink:type="resource" xlink:label="label_s2md_c7439" xml:lang="en" xlink:role="http://www.eurofiling.info/xbrl/role/rc-code">C1190</label:label>
    <gen:arc xlink:type="arc" xlink:arcrole="http://xbrl.org/arcrole/2008/element-label" xlink:from="loc_s2md_c7439" xlink:to="label_s2md_c7439" />
    <link:loc xlink:type="locator" xlink:href="s.27.01.01.20-rend.xml#s2md_c7440" xlink:label="loc_s2md_c7440" />
    <label:label xlink:type="resource" xlink:label="label_s2md_c7440" xml:lang="en" xlink:role="http://www.eurofiling.info/xbrl/role/rc-code">C1200</label:label>
    <gen:arc xlink:type="arc" xlink:arcrole="http://xbrl.org/arcrole/2008/element-label" xlink:from="loc_s2md_c7440" xlink:to="label_s2md_c7440" />
    <link:loc xlink:type="locator" xlink:href="s.27.01.01.20-rend.xml#s2md_c7442" xlink:label="loc_s2md_c7442" />
    <label:label xlink:type="resource" xlink:label="label_s2md_c7442" xml:lang="en" xlink:role="http://www.eurofiling.info/xbrl/role/rc-code">C1230</label:label>
    <gen:arc xlink:type="arc" xlink:arcrole="http://xbrl.org/arcrole/2008/element-label" xlink:from="loc_s2md_c7442" xlink:to="label_s2md_c7442" />
    <link:loc xlink:type="locator" xlink:href="s.27.01.01.20-rend.xml#s2md_c7443" xlink:label="loc_s2md_c7443" />
    <label:label xlink:type="resource" xlink:label="label_s2md_c7443" xml:lang="en" xlink:role="http://www.eurofiling.info/xbrl/role/rc-code">C1240</label:label>
    <gen:arc xlink:type="arc" xlink:arcrole="http://xbrl.org/arcrole/2008/element-label" xlink:from="loc_s2md_c7443" xlink:to="label_s2md_c7443" />
    <link:loc xlink:type="locator" xlink:href="s.27.01.01.20-rend.xml#s2md_c7445" xlink:label="loc_s2md_c7445" />
    <label:label xlink:type="resource" xlink:label="label_s2md_c7445" xml:lang="en" xlink:role="http://www.eurofiling.info/xbrl/role/rc-code">C1250</label:label>
    <gen:arc xlink:type="arc" xlink:arcrole="http://xbrl.org/arcrole/2008/element-label" xlink:from="loc_s2md_c7445" xlink:to="label_s2md_c7445" />
    <link:loc xlink:type="locator" xlink:href="s.27.01.01.20-rend.xml#s2md_c7446" xlink:label="loc_s2md_c7446" />
    <label:label xlink:type="resource" xlink:label="label_s2md_c7446" xml:lang="en" xlink:role="http://www.eurofiling.info/xbrl/role/rc-code">C1260</label:label>
    <gen:arc xlink:type="arc" xlink:arcrole="http://xbrl.org/arcrole/2008/element-label" xlink:from="loc_s2md_c7446" xlink:to="label_s2md_c7446" />
    <link:loc xlink:type="locator" xlink:href="s.27.01.01.20-rend.xml#s2md_c7447" xlink:label="loc_s2md_c7447" />
    <label:label xlink:type="resource" xlink:label="label_s2md_c7447" xml:lang="en" xlink:role="http://www.eurofiling.info/xbrl/role/rc-code">C1270</label:label>
    <gen:arc xlink:type="arc" xlink:arcrole="http://xbrl.org/arcrole/2008/element-label" xlink:from="loc_s2md_c7447" xlink:to="label_s2md_c7447" />
    <link:loc xlink:type="locator" xlink:href="s.27.01.01.20-rend.xml#s2md_c7448" xlink:label="loc_s2md_c7448" />
    <label:label xlink:type="resource" xlink:label="label_s2md_c7448" xml:lang="en" xlink:role="http://www.eurofiling.info/xbrl/role/rc-code">C1280</label:label>
    <gen:arc xlink:type="arc" xlink:arcrole="http://xbrl.org/arcrole/2008/element-label" xlink:from="loc_s2md_c7448" xlink:to="label_s2md_c7448" />
    <link:loc xlink:type="locator" xlink:href="s.27.01.01.20-rend.xml#s2md_c7449" xlink:label="loc_s2md_c7449" />
    <label:label xlink:type="resource" xlink:label="label_s2md_c7449" xml:lang="en" xlink:role="http://www.eurofiling.info/xbrl/role/rc-code">C1290</label:label>
    <gen:arc xlink:type="arc" xlink:arcrole="http://xbrl.org/arcrole/2008/element-label" xlink:from="loc_s2md_c7449" xlink:to="label_s2md_c7449" />
    <link:loc xlink:type="locator" xlink:href="s.27.01.01.20-rend.xml#s2md_c7450" xlink:label="loc_s2md_c7450" />
    <label:label xlink:type="resource" xlink:label="label_s2md_c7450" xml:lang="en" xlink:role="http://www.eurofiling.info/xbrl/role/rc-code">C1300</label:label>
    <gen:arc xlink:type="arc" xlink:arcrole="http://xbrl.org/arcrole/2008/element-label" xlink:from="loc_s2md_c7450" xlink:to="label_s2md_c7450" />
    <link:loc xlink:type="locator" xlink:href="s.27.01.01.20-rend.xml#s2md_c7452" xlink:label="loc_s2md_c7452" />
    <label:label xlink:type="resource" xlink:label="label_s2md_c7452" xml:lang="en" xlink:role="http://www.eurofiling.info/xbrl/role/rc-code">R3300</label:label>
    <gen:arc xlink:type="arc" xlink:arcrole="http://xbrl.org/arcrole/2008/element-label" xlink:from="loc_s2md_c7452" xlink:to="label_s2md_c7452" />
    <link:loc xlink:type="locator" xlink:href="s.27.01.01.20-rend.xml#s2md_c7453" xlink:label="loc_s2md_c7453" />
    <label:label xlink:type="resource" xlink:label="label_s2md_c7453" xml:lang="en" xlink:role="http://www.eurofiling.info/xbrl/role/rc-code">R3310</label:label>
    <gen:arc xlink:type="arc" xlink:arcrole="http://xbrl.org/arcrole/2008/element-label" xlink:from="loc_s2md_c7453" xlink:to="label_s2md_c7453" />
    <link:loc xlink:type="locator" xlink:href="s.27.01.01.20-rend.xml#s2md_c7454" xlink:label="loc_s2md_c7454" />
    <label:label xlink:type="resource" xlink:label="label_s2md_c7454" xml:lang="en" xlink:role="http://www.eurofiling.info/xbrl/role/rc-code">R3320</label:label>
    <gen:arc xlink:type="arc" xlink:arcrole="http://xbrl.org/arcrole/2008/element-label" xlink:from="loc_s2md_c7454" xlink:to="label_s2md_c7454" />
    <link:loc xlink:type="locator" xlink:href="s.27.01.01.20-rend.xml#s2md_c7455" xlink:label="loc_s2md_c7455" />
    <label:label xlink:type="resource" xlink:label="label_s2md_c7455" xml:lang="en" xlink:role="http://www.eurofiling.info/xbrl/role/rc-code">R3330</label:label>
    <gen:arc xlink:type="arc" xlink:arcrole="http://xbrl.org/arcrole/2008/element-label" xlink:from="loc_s2md_c7455" xlink:to="label_s2md_c7455" />
    <link:loc xlink:type="locator" xlink:href="s.27.01.01.20-rend.xml#s2md_c7456" xlink:label="loc_s2md_c7456" />
    <label:label xlink:type="resource" xlink:label="label_s2md_c7456" xml:lang="en" xlink:role="http://www.eurofiling.info/xbrl/role/rc-code">R3340</label:label>
    <gen:arc xlink:type="arc" xlink:arcrole="http://xbrl.org/arcrole/2008/element-label" xlink:from="loc_s2md_c7456" xlink:to="label_s2md_c7456" />
    <link:loc xlink:type="locator" xlink:href="s.27.01.01.20-rend.xml#s2md_c7457" xlink:label="loc_s2md_c7457" />
    <label:label xlink:type="resource" xlink:label="label_s2md_c7457" xml:lang="en" xlink:role="http://www.eurofiling.info/xbrl/role/rc-code">R3350</label:label>
    <gen:arc xlink:type="arc" xlink:arcrole="http://xbrl.org/arcrole/2008/element-label" xlink:from="loc_s2md_c7457" xlink:to="label_s2md_c7457" />
    <link:loc xlink:type="locator" xlink:href="s.27.01.01.20-rend.xml#s2md_c7458" xlink:label="loc_s2md_c7458" />
    <label:label xlink:type="resource" xlink:label="label_s2md_c7458" xml:lang="en" xlink:role="http://www.eurofiling.info/xbrl/role/rc-code">R3360</label:label>
    <gen:arc xlink:type="arc" xlink:arcrole="http://xbrl.org/arcrole/2008/element-label" xlink:from="loc_s2md_c7458" xlink:to="label_s2md_c7458" />
    <link:loc xlink:type="locator" xlink:href="s.27.01.01.20-rend.xml#s2md_c7459" xlink:label="loc_s2md_c7459" />
    <label:label xlink:type="resource" xlink:label="label_s2md_c7459" xml:lang="en" xlink:role="http://www.eurofiling.info/xbrl/role/rc-code">R3370</label:label>
    <gen:arc xlink:type="arc" xlink:arcrole="http://xbrl.org/arcrole/2008/element-label" xlink:from="loc_s2md_c7459" xlink:to="label_s2md_c7459" />
    <link:loc xlink:type="locator" xlink:href="s.27.01.01.20-rend.xml#s2md_c7460" xlink:label="loc_s2md_c7460" />
    <label:label xlink:type="resource" xlink:label="label_s2md_c7460" xml:lang="en" xlink:role="http://www.eurofiling.info/xbrl/role/rc-code">R3380</label:label>
    <gen:arc xlink:type="arc" xlink:arcrole="http://xbrl.org/arcrole/2008/element-label" xlink:from="loc_s2md_c7460" xlink:to="label_s2md_c7460" />
    <link:loc xlink:type="locator" xlink:href="s.27.01.01.20-rend.xml#s2md_c7461" xlink:label="loc_s2md_c7461" />
    <label:label xlink:type="resource" xlink:label="label_s2md_c7461" xml:lang="en" xlink:role="http://www.eurofiling.info/xbrl/role/rc-code">R3390</label:label>
    <gen:arc xlink:type="arc" xlink:arcrole="http://xbrl.org/arcrole/2008/element-label" xlink:from="loc_s2md_c7461" xlink:to="label_s2md_c7461" />
    <link:loc xlink:type="locator" xlink:href="s.27.01.01.20-rend.xml#s2md_c7462" xlink:label="loc_s2md_c7462" />
    <label:label xlink:type="resource" xlink:label="label_s2md_c7462" xml:lang="en" xlink:role="http://www.eurofiling.info/xbrl/role/rc-code">R3400</label:label>
    <gen:arc xlink:type="arc" xlink:arcrole="http://xbrl.org/arcrole/2008/element-label" xlink:from="loc_s2md_c7462" xlink:to="label_s2md_c7462" />
    <link:loc xlink:type="locator" xlink:href="s.27.01.01.20-rend.xml#s2md_c7463" xlink:label="loc_s2md_c7463" />
    <label:label xlink:type="resource" xlink:label="label_s2md_c7463" xml:lang="en" xlink:role="http://www.eurofiling.info/xbrl/role/rc-code">R3410</label:label>
    <gen:arc xlink:type="arc" xlink:arcrole="http://xbrl.org/arcrole/2008/element-label" xlink:from="loc_s2md_c7463" xlink:to="label_s2md_c7463" />
    <link:loc xlink:type="locator" xlink:href="s.27.01.01.20-rend.xml#s2md_c7464" xlink:label="loc_s2md_c7464" />
    <label:label xlink:type="resource" xlink:label="label_s2md_c7464" xml:lang="en" xlink:role="http://www.eurofiling.info/xbrl/role/rc-code">R3420</label:label>
    <gen:arc xlink:type="arc" xlink:arcrole="http://xbrl.org/arcrole/2008/element-label" xlink:from="loc_s2md_c7464" xlink:to="label_s2md_c7464" />
    <link:loc xlink:type="locator" xlink:href="s.27.01.01.20-rend.xml#s2md_c7465" xlink:label="loc_s2md_c7465" />
    <label:label xlink:type="resource" xlink:label="label_s2md_c7465" xml:lang="en" xlink:role="http://www.eurofiling.info/xbrl/role/rc-code">R3430</label:label>
    <gen:arc xlink:type="arc" xlink:arcrole="http://xbrl.org/arcrole/2008/element-label" xlink:from="loc_s2md_c7465" xlink:to="label_s2md_c7465" />
    <link:loc xlink:type="locator" xlink:href="s.27.01.01.20-rend.xml#s2md_c7466" xlink:label="loc_s2md_c7466" />
    <label:label xlink:type="resource" xlink:label="label_s2md_c7466" xml:lang="en" xlink:role="http://www.eurofiling.info/xbrl/role/rc-code">R3440</label:label>
    <gen:arc xlink:type="arc" xlink:arcrole="http://xbrl.org/arcrole/2008/element-label" xlink:from="loc_s2md_c7466" xlink:to="label_s2md_c7466" />
    <link:loc xlink:type="locator" xlink:href="s.27.01.01.20-rend.xml#s2md_c7467" xlink:label="loc_s2md_c7467" />
    <label:label xlink:type="resource" xlink:label="label_s2md_c7467" xml:lang="en" xlink:role="http://www.eurofiling.info/xbrl/role/rc-code">R3450</label:label>
    <gen:arc xlink:type="arc" xlink:arcrole="http://xbrl.org/arcrole/2008/element-label" xlink:from="loc_s2md_c7467" xlink:to="label_s2md_c7467" />
    <link:loc xlink:type="locator" xlink:href="s.27.01.01.20-rend.xml#s2md_c7468" xlink:label="loc_s2md_c7468" />
    <label:label xlink:type="resource" xlink:label="label_s2md_c7468" xml:lang="en" xlink:role="http://www.eurofiling.info/xbrl/role/rc-code">R3460</label:label>
    <gen:arc xlink:type="arc" xlink:arcrole="http://xbrl.org/arcrole/2008/element-label" xlink:from="loc_s2md_c7468" xlink:to="label_s2md_c7468" />
    <link:loc xlink:type="locator" xlink:href="s.27.01.01.20-rend.xml#s2md_c7469" xlink:label="loc_s2md_c7469" />
    <label:label xlink:type="resource" xlink:label="label_s2md_c7469" xml:lang="en" xlink:role="http://www.eurofiling.info/xbrl/role/rc-code">R3470</label:label>
    <gen:arc xlink:type="arc" xlink:arcrole="http://xbrl.org/arcrole/2008/element-label" xlink:from="loc_s2md_c7469" xlink:to="label_s2md_c7469" />
    <link:loc xlink:type="locator" xlink:href="s.27.01.01.20-rend.xml#s2md_c7470" xlink:label="loc_s2md_c7470" />
    <label:label xlink:type="resource" xlink:label="label_s2md_c7470" xml:lang="en" xlink:role="http://www.eurofiling.info/xbrl/role/rc-code">R3480</label:label>
    <gen:arc xlink:type="arc" xlink:arcrole="http://xbrl.org/arcrole/2008/element-label" xlink:from="loc_s2md_c7470" xlink:to="label_s2md_c7470" />
    <link:loc xlink:type="locator" xlink:href="s.27.01.01.20-rend.xml#s2md_c7471" xlink:label="loc_s2md_c7471" />
    <label:label xlink:type="resource" xlink:label="label_s2md_c7471" xml:lang="en" xlink:role="http://www.eurofiling.info/xbrl/role/rc-code">R3490</label:label>
    <gen:arc xlink:type="arc" xlink:arcrole="http://xbrl.org/arcrole/2008/element-label" xlink:from="loc_s2md_c7471" xlink:to="label_s2md_c7471" />
    <link:loc xlink:type="locator" xlink:href="s.27.01.01.20-rend.xml#s2md_c7472" xlink:label="loc_s2md_c7472" />
    <label:label xlink:type="resource" xlink:label="label_s2md_c7472" xml:lang="en" xlink:role="http://www.eurofiling.info/xbrl/role/rc-code">R3500</label:label>
    <gen:arc xlink:type="arc" xlink:arcrole="http://xbrl.org/arcrole/2008/element-label" xlink:from="loc_s2md_c7472" xlink:to="label_s2md_c7472" />
    <link:loc xlink:type="locator" xlink:href="s.27.01.01.20-rend.xml#s2md_c7473" xlink:label="loc_s2md_c7473" />
    <label:label xlink:type="resource" xlink:label="label_s2md_c7473" xml:lang="en" xlink:role="http://www.eurofiling.info/xbrl/role/rc-code">R3510</label:label>
    <gen:arc xlink:type="arc" xlink:arcrole="http://xbrl.org/arcrole/2008/element-label" xlink:from="loc_s2md_c7473" xlink:to="label_s2md_c7473" />
    <link:loc xlink:type="locator" xlink:href="s.27.01.01.20-rend.xml#s2md_c7474" xlink:label="loc_s2md_c7474" />
    <label:label xlink:type="resource" xlink:label="label_s2md_c7474" xml:lang="en" xlink:role="http://www.eurofiling.info/xbrl/role/rc-code">R3520</label:label>
    <gen:arc xlink:type="arc" xlink:arcrole="http://xbrl.org/arcrole/2008/element-label" xlink:from="loc_s2md_c7474" xlink:to="label_s2md_c7474" />
    <link:loc xlink:type="locator" xlink:href="s.27.01.01.20-rend.xml#s2md_c7475" xlink:label="loc_s2md_c7475" />
    <label:label xlink:type="resource" xlink:label="label_s2md_c7475" xml:lang="en" xlink:role="http://www.eurofiling.info/xbrl/role/rc-code">R3530</label:label>
    <gen:arc xlink:type="arc" xlink:arcrole="http://xbrl.org/arcrole/2008/element-label" xlink:from="loc_s2md_c7475" xlink:to="label_s2md_c7475" />
    <link:loc xlink:type="locator" xlink:href="s.27.01.01.20-rend.xml#s2md_c7476" xlink:label="loc_s2md_c7476" />
    <label:label xlink:type="resource" xlink:label="label_s2md_c7476" xml:lang="en" xlink:role="http://www.eurofiling.info/xbrl/role/rc-code">R3540</label:label>
    <gen:arc xlink:type="arc" xlink:arcrole="http://xbrl.org/arcrole/2008/element-label" xlink:from="loc_s2md_c7476" xlink:to="label_s2md_c7476" />
    <link:loc xlink:type="locator" xlink:href="s.27.01.01.20-rend.xml#s2md_c7477" xlink:label="loc_s2md_c7477" />
    <label:label xlink:type="resource" xlink:label="label_s2md_c7477" xml:lang="en" xlink:role="http://www.eurofiling.info/xbrl/role/rc-code">R3550</label:label>
    <gen:arc xlink:type="arc" xlink:arcrole="http://xbrl.org/arcrole/2008/element-label" xlink:from="loc_s2md_c7477" xlink:to="label_s2md_c7477" />
    <link:loc xlink:type="locator" xlink:href="s.27.01.01.20-rend.xml#s2md_c7478" xlink:label="loc_s2md_c7478" />
    <label:label xlink:type="resource" xlink:label="label_s2md_c7478" xml:lang="en" xlink:role="http://www.eurofiling.info/xbrl/role/rc-code">R3560</label:label>
    <gen:arc xlink:type="arc" xlink:arcrole="http://xbrl.org/arcrole/2008/element-label" xlink:from="loc_s2md_c7478" xlink:to="label_s2md_c7478" />
    <link:loc xlink:type="locator" xlink:href="s.27.01.01.20-rend.xml#s2md_c7479" xlink:label="loc_s2md_c7479" />
    <label:label xlink:type="resource" xlink:label="label_s2md_c7479" xml:lang="en" xlink:role="http://www.eurofiling.info/xbrl/role/rc-code">R3570</label:label>
    <gen:arc xlink:type="arc" xlink:arcrole="http://xbrl.org/arcrole/2008/element-label" xlink:from="loc_s2md_c7479" xlink:to="label_s2md_c7479" />
    <link:loc xlink:type="locator" xlink:href="s.27.01.01.20-rend.xml#s2md_c7480" xlink:label="loc_s2md_c7480" />
    <label:label xlink:type="resource" xlink:label="label_s2md_c7480" xml:lang="en" xlink:role="http://www.eurofiling.info/xbrl/role/rc-code">R3580</label:label>
    <gen:arc xlink:type="arc" xlink:arcrole="http://xbrl.org/arcrole/2008/element-label" xlink:from="loc_s2md_c7480" xlink:to="label_s2md_c7480" />
    <link:loc xlink:type="locator" xlink:href="s.27.01.01.20-rend.xml#s2md_c7481" xlink:label="loc_s2md_c7481" />
    <label:label xlink:type="resource" xlink:label="label_s2md_c7481" xml:lang="en" xlink:role="http://www.eurofiling.info/xbrl/role/rc-code">R3590</label:label>
    <gen:arc xlink:type="arc" xlink:arcrole="http://xbrl.org/arcrole/2008/element-label" xlink:from="loc_s2md_c7481" xlink:to="label_s2md_c7481" />
    <link:loc xlink:type="locator" xlink:href="s.27.01.01.20-rend.xml#s2md_c7482" xlink:label="loc_s2md_c7482" />
    <label:label xlink:type="resource" xlink:label="label_s2md_c7482" xml:lang="en" xlink:role="http://www.eurofiling.info/xbrl/role/rc-code">R3600</label:label>
    <gen:arc xlink:type="arc" xlink:arcrole="http://xbrl.org/arcrole/2008/element-label" xlink:from="loc_s2md_c7482" xlink:to="label_s2md_c7482" />
    <link:loc xlink:type="locator" xlink:href="s.27.01.01.20-rend.xml#s2md_c7483" xlink:label="loc_s2md_c7483" />
    <label:label xlink:type="resource" xlink:label="label_s2md_c7483" xml:lang="en" xlink:role="http://www.eurofiling.info/xbrl/role/rc-code">R3610</label:label>
    <gen:arc xlink:type="arc" xlink:arcrole="http://xbrl.org/arcrole/2008/element-label" xlink:from="loc_s2md_c7483" xlink:to="label_s2md_c7483" />
    <link:loc xlink:type="locator" xlink:href="s.27.01.01.20-rend.xml#s2md_c7484" xlink:label="loc_s2md_c7484" />
    <label:label xlink:type="resource" xlink:label="label_s2md_c7484" xml:lang="en" xlink:role="http://www.eurofiling.info/xbrl/role/rc-code">R3620</label:label>
    <gen:arc xlink:type="arc" xlink:arcrole="http://xbrl.org/arcrole/2008/element-label" xlink:from="loc_s2md_c7484" xlink:to="label_s2md_c7484" />
    <link:loc xlink:type="locator" xlink:href="s.27.01.01.20-rend.xml#s2md_c7485" xlink:label="loc_s2md_c7485" />
    <label:label xlink:type="resource" xlink:label="label_s2md_c7485" xml:lang="en" xlink:role="http://www.eurofiling.info/xbrl/role/rc-code">R3630</label:label>
    <gen:arc xlink:type="arc" xlink:arcrole="http://xbrl.org/arcrole/2008/element-label" xlink:from="loc_s2md_c7485" xlink:to="label_s2md_c7485" />
    <label:label xlink:type="resource" xlink:label="label_s2md_tS.27.01.01.20_1" xml:lang="en" xlink:role="http://www.eurofiling.info/xbrl/role/filing-indicator-code">S.27.01</label:label>
    <gen:arc xlink:type="arc" xlink:arcrole="http://xbrl.org/arcrole/2008/element-label" xlink:from="loc_s2md_tS.27.01.01.20" xlink:to="label_s2md_tS.27.01.01.20_1" />
  </gen:link>
</link:linkbase>