<?xml version="1.0" encoding="UTF-8"?>
<!--(C) EIOPA - XBRL Taxonomy-->
<?officialURI http://eiopa.europa.eu/eu/xbrl/s2md/fws/solvency/solvency2/2019-07-15/tab/s.19.01.01.08/s.19.01.01.08-lab-codes.xml?>
<?taxonomy-version 2.4.0?>
<?taxonomy-date 2019-07-15?>
<link:linkbase xmlns:xsi="http://www.w3.org/2001/XMLSchema-instance" xmlns:xlink="http://www.w3.org/1999/xlink" xmlns:link="http://www.xbrl.org/2003/linkbase" xmlns:gen="http://xbrl.org/2008/generic" xmlns:label="http://xbrl.org/2008/label" xsi:schemaLocation="http://www.xbrl.org/2003/linkbase http://www.xbrl.org/2003/xbrl-linkbase-2003-12-31.xsd http://xbrl.org/2008/generic http://www.xbrl.org/2008/generic-link.xsd http://xbrl.org/2008/label http://www.xbrl.org/2008/generic-label.xsd">
  <link:arcroleRef arcroleURI="http://xbrl.org/arcrole/2008/element-label" xlink:type="simple" xlink:href="http://www.xbrl.org/2008/generic-label.xsd#element-label" />
  <link:roleRef roleURI="http://www.eurofiling.info/xbrl/role/filing-indicator-code" xlink:type="simple" xlink:href="http://www.eurofiling.info/eu/fr/xbrl/ext/model.xsd#filing-indicator-code" />
  <link:roleRef roleURI="http://www.eurofiling.info/xbrl/role/rc-code" xlink:type="simple" xlink:href="http://www.eurofiling.info/eu/fr/xbrl/ext/model.xsd#rc-code" />
  <gen:link xlink:type="extended" xlink:role="http://www.xbrl.org/2003/role/link">
    <link:loc xlink:type="locator" xlink:href="s.19.01.01.08-rend.xml#s2md_tS.19.01.01.08" xlink:label="loc_s2md_tS.19.01.01.08" />
    <label:label xlink:type="resource" xlink:label="label_s2md_tS.19.01.01.08" xml:lang="en" xlink:role="http://www.eurofiling.info/xbrl/role/rc-code">S.19.01.01.08</label:label>
    <gen:arc xlink:type="arc" xlink:arcrole="http://xbrl.org/arcrole/2008/element-label" xlink:from="loc_s2md_tS.19.01.01.08" xlink:to="label_s2md_tS.19.01.01.08" />
    <link:loc xlink:type="locator" xlink:href="s.19.01.01.08-rend.xml#s2md_c3449" xlink:label="loc_s2md_c3449" />
    <label:label xlink:type="resource" xlink:label="label_s2md_c3449" xml:lang="en" xlink:role="http://www.eurofiling.info/xbrl/role/rc-code">C0760</label:label>
    <gen:arc xlink:type="arc" xlink:arcrole="http://xbrl.org/arcrole/2008/element-label" xlink:from="loc_s2md_c3449" xlink:to="label_s2md_c3449" />
    <link:loc xlink:type="locator" xlink:href="s.19.01.01.08-rend.xml#s2md_c3450" xlink:label="loc_s2md_c3450" />
    <label:label xlink:type="resource" xlink:label="label_s2md_c3450" xml:lang="en" xlink:role="http://www.eurofiling.info/xbrl/role/rc-code">C0770</label:label>
    <gen:arc xlink:type="arc" xlink:arcrole="http://xbrl.org/arcrole/2008/element-label" xlink:from="loc_s2md_c3450" xlink:to="label_s2md_c3450" />
    <link:loc xlink:type="locator" xlink:href="s.19.01.01.08-rend.xml#s2md_c3451" xlink:label="loc_s2md_c3451" />
    <label:label xlink:type="resource" xlink:label="label_s2md_c3451" xml:lang="en" xlink:role="http://www.eurofiling.info/xbrl/role/rc-code">R0300</label:label>
    <gen:arc xlink:type="arc" xlink:arcrole="http://xbrl.org/arcrole/2008/element-label" xlink:from="loc_s2md_c3451" xlink:to="label_s2md_c3451" />
    <link:loc xlink:type="locator" xlink:href="s.19.01.01.08-rend.xml#s2md_c3452" xlink:label="loc_s2md_c3452" />
    <label:label xlink:type="resource" xlink:label="label_s2md_c3452" xml:lang="en" xlink:role="http://www.eurofiling.info/xbrl/role/rc-code">R0310</label:label>
    <gen:arc xlink:type="arc" xlink:arcrole="http://xbrl.org/arcrole/2008/element-label" xlink:from="loc_s2md_c3452" xlink:to="label_s2md_c3452" />
    <link:loc xlink:type="locator" xlink:href="s.19.01.01.08-rend.xml#s2md_c3453" xlink:label="loc_s2md_c3453" />
    <label:label xlink:type="resource" xlink:label="label_s2md_c3453" xml:lang="en" xlink:role="http://www.eurofiling.info/xbrl/role/rc-code">R0320</label:label>
    <gen:arc xlink:type="arc" xlink:arcrole="http://xbrl.org/arcrole/2008/element-label" xlink:from="loc_s2md_c3453" xlink:to="label_s2md_c3453" />
    <link:loc xlink:type="locator" xlink:href="s.19.01.01.08-rend.xml#s2md_c3454" xlink:label="loc_s2md_c3454" />
    <label:label xlink:type="resource" xlink:label="label_s2md_c3454" xml:lang="en" xlink:role="http://www.eurofiling.info/xbrl/role/rc-code">R0330</label:label>
    <gen:arc xlink:type="arc" xlink:arcrole="http://xbrl.org/arcrole/2008/element-label" xlink:from="loc_s2md_c3454" xlink:to="label_s2md_c3454" />
    <link:loc xlink:type="locator" xlink:href="s.19.01.01.08-rend.xml#s2md_c3455" xlink:label="loc_s2md_c3455" />
    <label:label xlink:type="resource" xlink:label="label_s2md_c3455" xml:lang="en" xlink:role="http://www.eurofiling.info/xbrl/role/rc-code">R0340</label:label>
    <gen:arc xlink:type="arc" xlink:arcrole="http://xbrl.org/arcrole/2008/element-label" xlink:from="loc_s2md_c3455" xlink:to="label_s2md_c3455" />
    <link:loc xlink:type="locator" xlink:href="s.19.01.01.08-rend.xml#s2md_c3456" xlink:label="loc_s2md_c3456" />
    <label:label xlink:type="resource" xlink:label="label_s2md_c3456" xml:lang="en" xlink:role="http://www.eurofiling.info/xbrl/role/rc-code">R0350</label:label>
    <gen:arc xlink:type="arc" xlink:arcrole="http://xbrl.org/arcrole/2008/element-label" xlink:from="loc_s2md_c3456" xlink:to="label_s2md_c3456" />
    <link:loc xlink:type="locator" xlink:href="s.19.01.01.08-rend.xml#s2md_c3457" xlink:label="loc_s2md_c3457" />
    <label:label xlink:type="resource" xlink:label="label_s2md_c3457" xml:lang="en" xlink:role="http://www.eurofiling.info/xbrl/role/rc-code">R0360</label:label>
    <gen:arc xlink:type="arc" xlink:arcrole="http://xbrl.org/arcrole/2008/element-label" xlink:from="loc_s2md_c3457" xlink:to="label_s2md_c3457" />
    <link:loc xlink:type="locator" xlink:href="s.19.01.01.08-rend.xml#s2md_c3458" xlink:label="loc_s2md_c3458" />
    <label:label xlink:type="resource" xlink:label="label_s2md_c3458" xml:lang="en" xlink:role="http://www.eurofiling.info/xbrl/role/rc-code">R0370</label:label>
    <gen:arc xlink:type="arc" xlink:arcrole="http://xbrl.org/arcrole/2008/element-label" xlink:from="loc_s2md_c3458" xlink:to="label_s2md_c3458" />
    <link:loc xlink:type="locator" xlink:href="s.19.01.01.08-rend.xml#s2md_c3459" xlink:label="loc_s2md_c3459" />
    <label:label xlink:type="resource" xlink:label="label_s2md_c3459" xml:lang="en" xlink:role="http://www.eurofiling.info/xbrl/role/rc-code">R0380</label:label>
    <gen:arc xlink:type="arc" xlink:arcrole="http://xbrl.org/arcrole/2008/element-label" xlink:from="loc_s2md_c3459" xlink:to="label_s2md_c3459" />
    <link:loc xlink:type="locator" xlink:href="s.19.01.01.08-rend.xml#s2md_c3460" xlink:label="loc_s2md_c3460" />
    <label:label xlink:type="resource" xlink:label="label_s2md_c3460" xml:lang="en" xlink:role="http://www.eurofiling.info/xbrl/role/rc-code">R0390</label:label>
    <gen:arc xlink:type="arc" xlink:arcrole="http://xbrl.org/arcrole/2008/element-label" xlink:from="loc_s2md_c3460" xlink:to="label_s2md_c3460" />
    <link:loc xlink:type="locator" xlink:href="s.19.01.01.08-rend.xml#s2md_c3461" xlink:label="loc_s2md_c3461" />
    <label:label xlink:type="resource" xlink:label="label_s2md_c3461" xml:lang="en" xlink:role="http://www.eurofiling.info/xbrl/role/rc-code">R0400</label:label>
    <gen:arc xlink:type="arc" xlink:arcrole="http://xbrl.org/arcrole/2008/element-label" xlink:from="loc_s2md_c3461" xlink:to="label_s2md_c3461" />
    <link:loc xlink:type="locator" xlink:href="s.19.01.01.08-rend.xml#s2md_c3462" xlink:label="loc_s2md_c3462" />
    <label:label xlink:type="resource" xlink:label="label_s2md_c3462" xml:lang="en" xlink:role="http://www.eurofiling.info/xbrl/role/rc-code">R0410</label:label>
    <gen:arc xlink:type="arc" xlink:arcrole="http://xbrl.org/arcrole/2008/element-label" xlink:from="loc_s2md_c3462" xlink:to="label_s2md_c3462" />
    <link:loc xlink:type="locator" xlink:href="s.19.01.01.08-rend.xml#s2md_c3463" xlink:label="loc_s2md_c3463" />
    <label:label xlink:type="resource" xlink:label="label_s2md_c3463" xml:lang="en" xlink:role="http://www.eurofiling.info/xbrl/role/rc-code">R0420</label:label>
    <gen:arc xlink:type="arc" xlink:arcrole="http://xbrl.org/arcrole/2008/element-label" xlink:from="loc_s2md_c3463" xlink:to="label_s2md_c3463" />
    <link:loc xlink:type="locator" xlink:href="s.19.01.01.08-rend.xml#s2md_c3464" xlink:label="loc_s2md_c3464" />
    <label:label xlink:type="resource" xlink:label="label_s2md_c3464" xml:lang="en" xlink:role="http://www.eurofiling.info/xbrl/role/rc-code">R0430</label:label>
    <gen:arc xlink:type="arc" xlink:arcrole="http://xbrl.org/arcrole/2008/element-label" xlink:from="loc_s2md_c3464" xlink:to="label_s2md_c3464" />
    <link:loc xlink:type="locator" xlink:href="s.19.01.01.08-rend.xml#s2md_c3465" xlink:label="loc_s2md_c3465" />
    <label:label xlink:type="resource" xlink:label="label_s2md_c3465" xml:lang="en" xlink:role="http://www.eurofiling.info/xbrl/role/rc-code">R0440</label:label>
    <gen:arc xlink:type="arc" xlink:arcrole="http://xbrl.org/arcrole/2008/element-label" xlink:from="loc_s2md_c3465" xlink:to="label_s2md_c3465" />
    <link:loc xlink:type="locator" xlink:href="s.19.01.01.08-rend.xml#s2md_c3466" xlink:label="loc_s2md_c3466" />
    <label:label xlink:type="resource" xlink:label="label_s2md_c3466" xml:lang="en" xlink:role="http://www.eurofiling.info/xbrl/role/rc-code">R0450</label:label>
    <gen:arc xlink:type="arc" xlink:arcrole="http://xbrl.org/arcrole/2008/element-label" xlink:from="loc_s2md_c3466" xlink:to="label_s2md_c3466" />
    <link:loc xlink:type="locator" xlink:href="s.19.01.01.08-rend.xml#s2md_c3467" xlink:label="loc_s2md_c3467" />
    <label:label xlink:type="resource" xlink:label="label_s2md_c3467" xml:lang="en" xlink:role="http://www.eurofiling.info/xbrl/role/rc-code">R0460</label:label>
    <gen:arc xlink:type="arc" xlink:arcrole="http://xbrl.org/arcrole/2008/element-label" xlink:from="loc_s2md_c3467" xlink:to="label_s2md_c3467" />
    <link:loc xlink:type="locator" xlink:href="s.19.01.01.08-rend.xml#s2md_a4" xlink:label="loc_s2md_a4" />
    <label:label xlink:type="resource" xlink:label="label_s2md_a4" xml:lang="en" xlink:role="http://www.eurofiling.info/xbrl/role/rc-code">Z0010</label:label>
    <gen:arc xlink:type="arc" xlink:arcrole="http://xbrl.org/arcrole/2008/element-label" xlink:from="loc_s2md_a4" xlink:to="label_s2md_a4" />
    <link:loc xlink:type="locator" xlink:href="s.19.01.01.08-rend.xml#s2md_a5" xlink:label="loc_s2md_a5" />
    <label:label xlink:type="resource" xlink:label="label_s2md_a5" xml:lang="en" xlink:role="http://www.eurofiling.info/xbrl/role/rc-code">Z0020</label:label>
    <gen:arc xlink:type="arc" xlink:arcrole="http://xbrl.org/arcrole/2008/element-label" xlink:from="loc_s2md_a5" xlink:to="label_s2md_a5" />
    <link:loc xlink:type="locator" xlink:href="s.19.01.01.08-rend.xml#s2md_a6" xlink:label="loc_s2md_a6" />
    <label:label xlink:type="resource" xlink:label="label_s2md_a6" xml:lang="en" xlink:role="http://www.eurofiling.info/xbrl/role/rc-code">Z0030</label:label>
    <gen:arc xlink:type="arc" xlink:arcrole="http://xbrl.org/arcrole/2008/element-label" xlink:from="loc_s2md_a6" xlink:to="label_s2md_a6" />
    <link:loc xlink:type="locator" xlink:href="s.19.01.01.08-rend.xml#s2md_a7" xlink:label="loc_s2md_a7" />
    <label:label xlink:type="resource" xlink:label="label_s2md_a7" xml:lang="en" xlink:role="http://www.eurofiling.info/xbrl/role/rc-code">Z0040</label:label>
    <gen:arc xlink:type="arc" xlink:arcrole="http://xbrl.org/arcrole/2008/element-label" xlink:from="loc_s2md_a7" xlink:to="label_s2md_a7" />
    <label:label xlink:type="resource" xlink:label="label_s2md_tS.19.01.01.08_1" xml:lang="en" xlink:role="http://www.eurofiling.info/xbrl/role/filing-indicator-code">S.19.01</label:label>
    <gen:arc xlink:type="arc" xlink:arcrole="http://xbrl.org/arcrole/2008/element-label" xlink:from="loc_s2md_tS.19.01.01.08" xlink:to="label_s2md_tS.19.01.01.08_1" />
  </gen:link>
</link:linkbase>