<?xml version="1.0" encoding="UTF-8"?>
<!--(C) EIOPA - XBRL Taxonomy-->
<?officialURI http://eiopa.europa.eu/eu/xbrl/s2md/fws/solvency/solvency2/2019-07-15/tab/t.99.01.01.01/t.99.01.01.01-lab-en.xml?>
<?taxonomy-version 2.4.0?>
<?taxonomy-date 2019-07-15?>
<link:linkbase xmlns:xsi="http://www.w3.org/2001/XMLSchema-instance" xmlns:xlink="http://www.w3.org/1999/xlink" xmlns:link="http://www.xbrl.org/2003/linkbase" xmlns:gen="http://xbrl.org/2008/generic" xmlns:label="http://xbrl.org/2008/label" xsi:schemaLocation="http://www.xbrl.org/2003/linkbase http://www.xbrl.org/2003/xbrl-linkbase-2003-12-31.xsd http://xbrl.org/2008/generic http://www.xbrl.org/2008/generic-link.xsd http://xbrl.org/2008/label http://www.xbrl.org/2008/generic-label.xsd">
  <link:arcroleRef arcroleURI="http://xbrl.org/arcrole/2008/element-label" xlink:type="simple" xlink:href="http://www.xbrl.org/2008/generic-label.xsd#element-label" />
  <link:roleRef roleURI="http://www.xbrl.org/2008/role/label" xlink:type="simple" xlink:href="http://www.xbrl.org/2008/generic-label.xsd#standard-label" />
  <link:roleRef roleURI="http://www.xbrl.org/2008/role/verboseLabel" xlink:type="simple" xlink:href="http://www.xbrl.org/2008/generic-label.xsd#verbose-label" />
  <gen:link xlink:type="extended" xlink:role="http://www.xbrl.org/2003/role/link">
    <link:loc xlink:type="locator" xlink:href="t.99.01.01.01-rend.xml#s2md_tT.99.01.01.01" xlink:label="loc_s2md_tT.99.01.01.01" />
    <label:label xlink:type="resource" xlink:label="label_s2md_tT.99.01.01.01" xml:lang="en" xlink:role="http://www.xbrl.org/2008/role/label">Technical table</label:label>
    <gen:arc xlink:type="arc" xlink:arcrole="http://xbrl.org/arcrole/2008/element-label" xlink:from="loc_s2md_tT.99.01.01.01" xlink:to="label_s2md_tT.99.01.01.01" />
    <label:label xlink:type="resource" xlink:label="label_s2md_tT.99.01.01.01_1" xml:lang="en" xlink:role="http://www.xbrl.org/2008/role/verboseLabel">T.99.01.01.01 Technical table</label:label>
    <gen:arc xlink:type="arc" xlink:arcrole="http://xbrl.org/arcrole/2008/element-label" xlink:from="loc_s2md_tT.99.01.01.01" xlink:to="label_s2md_tT.99.01.01.01_1" />
    <link:loc xlink:type="locator" xlink:href="t.99.01.01.01-rend.xml#s2md_a1" xlink:label="loc_s2md_a1" />
    <label:label xlink:type="resource" xlink:label="label_s2md_a1" xml:lang="en" xlink:role="http://www.xbrl.org/2008/role/label">Columns</label:label>
    <gen:arc xlink:type="arc" xlink:arcrole="http://xbrl.org/arcrole/2008/element-label" xlink:from="loc_s2md_a1" xlink:to="label_s2md_a1" />
    <link:loc xlink:type="locator" xlink:href="t.99.01.01.01-rend.xml#s2md_c9696" xlink:label="loc_s2md_c9696" />
    <label:label xlink:type="resource" xlink:label="label_s2md_c9696" xml:lang="en" xlink:role="http://www.xbrl.org/2008/role/label">Comment</label:label>
    <gen:arc xlink:type="arc" xlink:arcrole="http://xbrl.org/arcrole/2008/element-label" xlink:from="loc_s2md_c9696" xlink:to="label_s2md_c9696" />
    <link:loc xlink:type="locator" xlink:href="t.99.01.01.01-rend.xml#s2md_c9697" xlink:label="loc_s2md_c9697" />
    <label:label xlink:type="resource" xlink:label="label_s2md_c9697" xml:lang="en" xlink:role="http://www.xbrl.org/2008/role/label">Monetary</label:label>
    <gen:arc xlink:type="arc" xlink:arcrole="http://xbrl.org/arcrole/2008/element-label" xlink:from="loc_s2md_c9697" xlink:to="label_s2md_c9697" />
    <link:loc xlink:type="locator" xlink:href="t.99.01.01.01-rend.xml#s2md_c9698" xlink:label="loc_s2md_c9698" />
    <label:label xlink:type="resource" xlink:label="label_s2md_c9698" xml:lang="en" xlink:role="http://www.xbrl.org/2008/role/label">String</label:label>
    <gen:arc xlink:type="arc" xlink:arcrole="http://xbrl.org/arcrole/2008/element-label" xlink:from="loc_s2md_c9698" xlink:to="label_s2md_c9698" />
    <link:loc xlink:type="locator" xlink:href="t.99.01.01.01-rend.xml#s2md_c9699" xlink:label="loc_s2md_c9699" />
    <label:label xlink:type="resource" xlink:label="label_s2md_c9699" xml:lang="en" xlink:role="http://www.xbrl.org/2008/role/label">Date</label:label>
    <gen:arc xlink:type="arc" xlink:arcrole="http://xbrl.org/arcrole/2008/element-label" xlink:from="loc_s2md_c9699" xlink:to="label_s2md_c9699" />
    <link:loc xlink:type="locator" xlink:href="t.99.01.01.01-rend.xml#s2md_c9700" xlink:label="loc_s2md_c9700" />
    <label:label xlink:type="resource" xlink:label="label_s2md_c9700" xml:lang="en" xlink:role="http://www.xbrl.org/2008/role/label">Integer</label:label>
    <gen:arc xlink:type="arc" xlink:arcrole="http://xbrl.org/arcrole/2008/element-label" xlink:from="loc_s2md_c9700" xlink:to="label_s2md_c9700" />
    <link:loc xlink:type="locator" xlink:href="t.99.01.01.01-rend.xml#s2md_c9701" xlink:label="loc_s2md_c9701" />
    <label:label xlink:type="resource" xlink:label="label_s2md_c9701" xml:lang="en" xlink:role="http://www.xbrl.org/2008/role/label">Decimal</label:label>
    <gen:arc xlink:type="arc" xlink:arcrole="http://xbrl.org/arcrole/2008/element-label" xlink:from="loc_s2md_c9701" xlink:to="label_s2md_c9701" />
    <link:loc xlink:type="locator" xlink:href="t.99.01.01.01-rend.xml#s2md_c9702" xlink:label="loc_s2md_c9702" />
    <label:label xlink:type="resource" xlink:label="label_s2md_c9702" xml:lang="en" xlink:role="http://www.xbrl.org/2008/role/label">Pure</label:label>
    <gen:arc xlink:type="arc" xlink:arcrole="http://xbrl.org/arcrole/2008/element-label" xlink:from="loc_s2md_c9702" xlink:to="label_s2md_c9702" />
    <link:loc xlink:type="locator" xlink:href="t.99.01.01.01-rend.xml#s2md_c9703" xlink:label="loc_s2md_c9703" />
    <label:label xlink:type="resource" xlink:label="label_s2md_c9703" xml:lang="en" xlink:role="http://www.xbrl.org/2008/role/label">Boolean</label:label>
    <gen:arc xlink:type="arc" xlink:arcrole="http://xbrl.org/arcrole/2008/element-label" xlink:from="loc_s2md_c9703" xlink:to="label_s2md_c9703" />
    <link:loc xlink:type="locator" xlink:href="t.99.01.01.01-rend.xml#s2md_a2" xlink:label="loc_s2md_a2" />
    <label:label xlink:type="resource" xlink:label="label_s2md_a2" xml:lang="en" xlink:role="http://www.xbrl.org/2008/role/label">Table</label:label>
    <gen:arc xlink:type="arc" xlink:arcrole="http://xbrl.org/arcrole/2008/element-label" xlink:from="loc_s2md_a2" xlink:to="label_s2md_a2" />
    <link:loc xlink:type="locator" xlink:href="t.99.01.01.01-rend.xml#s2md_a3" xlink:label="loc_s2md_a3" />
    <label:label xlink:type="resource" xlink:label="label_s2md_a3" xml:lang="en" xlink:role="http://www.xbrl.org/2008/role/label">X axis</label:label>
    <gen:arc xlink:type="arc" xlink:arcrole="http://xbrl.org/arcrole/2008/element-label" xlink:from="loc_s2md_a3" xlink:to="label_s2md_a3" />
    <link:loc xlink:type="locator" xlink:href="t.99.01.01.01-rend.xml#s2md_a4" xlink:label="loc_s2md_a4" />
    <label:label xlink:type="resource" xlink:label="label_s2md_a4" xml:lang="en" xlink:role="http://www.xbrl.org/2008/role/label">Y axis</label:label>
    <gen:arc xlink:type="arc" xlink:arcrole="http://xbrl.org/arcrole/2008/element-label" xlink:from="loc_s2md_a4" xlink:to="label_s2md_a4" />
    <link:loc xlink:type="locator" xlink:href="t.99.01.01.01-rend.xml#s2md_a5" xlink:label="loc_s2md_a5" />
    <label:label xlink:type="resource" xlink:label="label_s2md_a5" xml:lang="en" xlink:role="http://www.xbrl.org/2008/role/label">Z axis</label:label>
    <gen:arc xlink:type="arc" xlink:arcrole="http://xbrl.org/arcrole/2008/element-label" xlink:from="loc_s2md_a5" xlink:to="label_s2md_a5" />
  </gen:link>
</link:linkbase>